unitree_legged_sdk-3.8.20231105.dist-info/top_level.txt
unitree_legged_sdk-3.8.20231105.dist-info/WHEEL
unitree_legged_sdk-3.8.20231105.dist-info/METADATA
unitree_legged_sdk-3.8.20231105.dist-info/LICENSE
unitree_legged_sdk-3.8.20231105.dist-info/RECORD
unitree_legged_sdk.libs/libstdc++-a9383cce.so.6.0.28
unitree_legged_sdk.libs/libgcc_s-a04fdf82.so.1
unitree_legged_sdk/robot_interface.cpython-39-x86_64-linux-gnu.so
