Metadata-Version: 2.1
Name: unitree-legged-sdk
Version: 3.8.20231105
Summary: The unitree_legged_sdk is mainly used for communication between PC and Controller board.It also can be used in other PCs with UDP.
Home-page: https://github.com/unitreerobotics/unitree_legged_sdk
Author: LJoson
Author-email: 1250377062@qq.com
Maintainer: Unitree Robotics
Maintainer-email: Laikago@unitree.cc
License: BSD-3
Platform: UNKNOWN
Classifier: Programming Language :: C++
Classifier: Programming Language :: Python :: 3
Classifier: Programming Language :: Python :: 3.6
Classifier: Programming Language :: Python :: 3.7
Classifier: Programming Language :: Python :: 3.8
Classifier: Programming Language :: Python :: 3.9
Classifier: Programming Language :: Python :: 3.10
Classifier: License :: OSI Approved :: BSD License
Classifier: Operating System :: OS Independent
Requires-Python: >=3.6
License-File: LICENSE
Requires-Dist: pybind11
Requires-Dist: auditwheel
Requires-Dist: twine
Requires-Dist: wheel
Requires-Dist: setuptools
